[ {
  "code" : "AUD",
  "exchangeRates" : {
    "SGD" : {
      "rate" : 0.86963007,
      "lastUpdated" : "2024-09-10"
    },
    "USD" : {
      "rate" : 0.66553064,
      "lastUpdated" : "2024-09-10"
    },
    "EUR" : {
      "rate" : 0.60270489,
      "lastUpdated" : "2024-09-10"
    },
    "GBP" : {
      "rate" : 0.50849969,
      "lastUpdated" : "2024-09-10"
    },
    "JPY" : {
      "rate" : 95.625216,
      "lastUpdated" : "2024-09-10"
    }
  }
}, {
  "code" : "SGD",
  "exchangeRates" : {
    "AUD" : {
      "rate" : 1.1497695,
      "lastUpdated" : "2024-09-10"
    },
    "USD" : {
      "rate" : 0.76531097,
      "lastUpdated" : "2024-09-10"
    },
    "EUR" : {
      "rate" : 0.69307465,
      "lastUpdated" : "2024-09-10"
    },
    "GBP" : {
      "rate" : 0.58472601,
      "lastUpdated" : "2024-09-10"
    },
    "JPY" : {
      "rate" : 109.95713,
      "lastUpdated" : "2024-09-10"
    }
  }
}, {
  "code" : "USD",
  "exchangeRates" : {
    "AUD" : {
      "rate" : 1.5023559,
      "lastUpdated" : "2024-09-10"
    },
    "SGD" : {
      "rate" : 1.3066584,
      "lastUpdated" : "2024-09-10"
    },
    "EUR" : {
      "rate" : 0.9056118,
      "lastUpdated" : "2024-09-10"
    },
    "GBP" : {
      "rate" : 0.76403714,
      "lastUpdated" : "2024-09-10"
    },
    "JPY" : {
      "rate" : 143.67641,
      "lastUpdated" : "2024-09-10"
    }
  }
}, {
  "code" : "EUR",
  "exchangeRates" : {
    "AUD" : {
      "rate" : 1.6588229,
      "lastUpdated" : "2024-09-10"
    },
    "SGD" : {
      "rate" : 1.442971,
      "lastUpdated" : "2024-09-10"
    },
    "USD" : {
      "rate" : 1.1043056,
      "lastUpdated" : "2024-09-10"
    },
    "GBP" : {
      "rate" : 0.84377413,
      "lastUpdated" : "2024-09-10"
    },
    "JPY" : {
      "rate" : 158.67326,
      "lastUpdated" : "2024-09-10"
    }
  }
}, {
  "code" : "GBP",
  "exchangeRates" : {
    "AUD" : {
      "rate" : 1.9654782,
      "lastUpdated" : "2024-09-10"
    },
    "SGD" : {
      "rate" : 1.710012,
      "lastUpdated" : "2024-09-10"
    },
    "USD" : {
      "rate" : 1.3087993,
      "lastUpdated" : "2024-09-10"
    },
    "EUR" : {
      "rate" : 1.1851513,
      "lastUpdated" : "2024-09-10"
    },
    "JPY" : {
      "rate" : 188.05181,
      "lastUpdated" : "2024-09-10"
    }
  }
}, {
  "code" : "JPY",
  "exchangeRates" : {
    "AUD" : {
      "rate" : 0.010458102,
      "lastUpdated" : "2024-09-10"
    },
    "SGD" : {
      "rate" : 0.009098581,
      "lastUpdated" : "2024-09-10"
    },
    "USD" : {
      "rate" : 0.006963396,
      "lastUpdated" : "2024-09-10"
    },
    "EUR" : {
      "rate" : 0.006304226,
      "lastUpdated" : "2024-09-10"
    },
    "GBP" : {
      "rate" : 0.00531968,
      "lastUpdated" : "2024-09-10"
    }
  }
} ]